skmine/__init__.py
skmine/base.py
skmine/callbacks.py
skmine/utils.py
skmine/datasets/__init__.py
skmine/datasets/_base.py
skmine/datasets/_samples_generator.py
skmine/datasets/conf.py
skmine/datasets/fimi.py
skmine/datasets/periodic.py
skmine/datasets/utils.py
skmine/emerging/__init__.py
skmine/emerging/mbdldorber.py
skmine/feature_extraction/__init__.py
skmine/feature_extraction/slim_vectorizer.py
skmine/graph/__init__.py
skmine/graph/graphmdl/__init__.py
skmine/graph/graphmdl/candidate.py
skmine/graph/graphmdl/code_table.py
skmine/graph/graphmdl/code_table_row.py
skmine/graph/graphmdl/graph_mdl.py
skmine/graph/graphmdl/label_codes.py
skmine/graph/graphmdl/utils.py
skmine/graph/graphmdl/test/__init__.py
skmine/graph/graphmdl/test/test_graph_mdl.py
skmine/itemsets/__init__.py
skmine/itemsets/lcm.py
skmine/itemsets/slim.py
skmine/itemsets/slim_classifier.py
skmine/periodic/__init__.py
skmine/periodic/candidate.py
skmine/periodic/candidate_pool.py
skmine/periodic/class_patterns.py
skmine/periodic/cycles.py
skmine/periodic/data_sequence.py
skmine/periodic/extract_cycles.py
skmine/periodic/pattern.py
skmine/periodic/pattern_collection.py
skmine/periodic/run_mine.py
skmine/preprocessing/__init__.py
skmine/preprocessing/mdlp_discretizer.py
scikit_mine-1.0.0.dist-info/LICENSE
scikit_mine-1.0.0.dist-info/METADATA
scikit_mine-1.0.0.dist-info/WHEEL
scikit_mine-1.0.0.dist-info/top_level.txt
scikit_mine-1.0.0.dist-info/RECORD
