Metadata-Version: 2.1
Name: scikit-mine
Version: 1.0.0
Summary: Pattern mining in Python
Home-page: https://github.com/scikit-mine/scikit-mine
Download-URL: https://github.com/scikit-mine/scikit-mine
Maintainer: scikit-mine team
Maintainer-email: skm-dev@inria.fr
License: new BSD
Classifier: Intended Audience :: Science/Research
Classifier: Intended Audience :: Developers
Classifier: License :: OSI Approved
Classifier: Programming Language :: Python
Classifier: Programming Language :: Python :: 3.11
Classifier: Programming Language :: Python :: 3.10
Classifier: Programming Language :: Python :: 3.9
Classifier: Programming Language :: Python :: 3.8
Classifier: Topic :: Software Development
Classifier: Topic :: Scientific/Engineering
Classifier: Operating System :: Microsoft :: Windows
Classifier: Operating System :: POSIX
Classifier: Operating System :: Unix
Classifier: Operating System :: MacOS
License-File: LICENSE
Requires-Dist: scipy (>=1.2.1)
Requires-Dist: pandas (>=1.0.0)
Requires-Dist: pyroaring (>=0.3.4)
Requires-Dist: joblib (>=0.11.1)
Requires-Dist: sortedcontainers (>=2.1.0)
Requires-Dist: dataclasses (>=0.6)
Requires-Dist: networkx
Requires-Dist: wget (>=3.2)
Requires-Dist: scikit-learn
Requires-Dist: graphviz
Requires-Dist: matplotlib
Requires-Dist: pydot
Provides-Extra: docs
Requires-Dist: sphinx ; extra == 'docs'
Requires-Dist: sphinx-gallery ; extra == 'docs'
Requires-Dist: sphinx-rtd-theme ; extra == 'docs'
Requires-Dist: numpydoc ; extra == 'docs'
Requires-Dist: matplotlib ; extra == 'docs'
Provides-Extra: tests
Requires-Dist: pytest ; extra == 'tests'
Requires-Dist: pytest-cov ; extra == 'tests'
